{"id":2,"university":{"fullName":"Arab Academy for Science and Technology (Alexandria)","shortName":"AAST Alexandria","region":"Africa and the Middle East","url":"http://www.aast.edu","myIcpcId":"312663","appearances":5,"wins":0,"gold":0,"silver":0,"bronze":0,"regionalChampionships":1},"team":{"name":"DebugMyHair","regionals":[],"openCupPlace":-1,"openCupTimes":0},"coach":{"name":"Abd El-Wahab Mohamed","altNames":["Mohamed Abd El-Wahab"],"tcHandle":"fegla","tcId":"20538097","tcRating":1339,"cfHandle":"fegla","cfRating":1591,"twitterHandle":"wahabfegla","achievements":[{"achievement":"World Finals coach (2010, 2012-2016)","priority":1010},{"achievement":"ACM ICPC Finalist (2002)","priority":1001}]},"contestants":[{"name":"Hegazi Ahmed Salem Ezzat Salem","altNames":["Ahmed Salem Ezzat Salem Hegazi"],"tcRating":-1,"cfRating":-1,"achievements":[{"achievement":"World Finals coach (2016)","priority":1001}]},{"name":"Ghallab Walid","altNames":["Walid Ghallab"],"tcRating":-1,"cfRating":-1,"achievements":[]},{"name":"Salama Youssef","altNames":["Youssef Salama"],"tcRating":-1,"cfHandle":"youssseeef","cfRating":1403,"achievements":[]}]}