{"id":76,"university":{"fullName":"Stanford University","shortName":"Stanford","region":"North America","hashTag":"#Stanford","url":"www.stanford.edu","appearances":18,"wins":0,"gold":1,"silver":3,"bronze":1,"regionalChampionships":-1},"team":{"name":"Stanford Cardinal","regionals":["The 2015 Pacific Northwest Regional Contest, 2nd"],"openCupPlace":-1},"coach":{"name":"Gerald Cain","altNames":[],"tcRating":-1,"cfRating":-1,"achievements":[]},"contestants":[{"name":"Hubert Teo","altNames":[],"tcRating":-1,"cfRating":-1,"achievements":[]},{"name":"Joshua Alman","altNames":[],"tcRating":-1,"cfRating":-1,"achievements":[]},{"name":"Yuetong Wang","altNames":[],"tcRating":-1,"cfRating":-1,"achievements":[]}]}